daphne/__init__.py
daphne/context/__init__.py
daphne/context/daphne_context.py
daphne/operator/__init__.py
daphne/operator/operation_node.py
daphne/operator/nodes/__init__.py
daphne/operator/nodes/cond.py
daphne/operator/nodes/do_while_loop.py
daphne/operator/nodes/for_loop.py
daphne/operator/nodes/frame.py
daphne/operator/nodes/function.py
daphne/operator/nodes/matrix.py
daphne/operator/nodes/multi_return.py
daphne/operator/nodes/scalar.py
daphne/operator/nodes/while_loop.py
daphne/script_building/__init__.py
daphne/script_building/dag.py
daphne/script_building/nested_script.py
daphne/script_building/script.py
daphne/utils/__init__.py
daphne/utils/analyzer.py
daphne/utils/consts.py
daphne/utils/daphnelib.py
daphne/utils/helpers.py
daphne_lib-0.3.0.dist-info/LICENSE.txt
daphne_lib-0.3.0.dist-info/METADATA
daphne_lib-0.3.0.dist-info/WHEEL
daphne_lib-0.3.0.dist-info/top_level.txt
daphne_lib-0.3.0.dist-info/RECORD
