Metadata-Version: 2.1
Name: daphne-lib
Version: 0.3.0
Summary: DaphneLib: Python API for DAPHNE
Author-email: The DAPHNE Consortium <daphne_dev@know-center.at>
License: Apache v2.0
Project-URL: Homepage, https://daphne-eu.eu/
Project-URL: Documentation, https://daphne-eu.github.io/daphne/DaphneLib/Overview/
Project-URL: Repository, https://github.com/daphne-eu/daphne
Project-URL: Issues, https://github.com/daphne-eu/daphne/issues
Project-URL: Changelog, https://github.com/daphne-eu/daphne/releases
Keywords: DAPHNE,Integrated Data Analysis Pipelines
Classifier: License :: OSI Approved :: Apache Software License
Classifier: Operating System :: POSIX :: Linux
Classifier: Topic :: Software Development
Classifier: Topic :: Software Development :: Libraries
Classifier: Topic :: Software Development :: Libraries :: Python Modules
Classifier: Topic :: System :: Distributed Computing
Classifier: Topic :: Scientific/Engineering
Classifier: Topic :: Scientific/Engineering :: Artificial Intelligence
Classifier: Topic :: Scientific/Engineering :: Mathematics
Requires-Python: >=3.8
License-File: LICENSE.txt
Requires-Dist: pandas
